pyportable_installer/__init__.py
pyportable_installer/__main__.py
pyportable_installer/_env.py
pyportable_installer/checkup/doctor.py
pyportable_installer/checkup/pretty_print.py
pyportable_installer/compilers/__init__.py
pyportable_installer/compilers/base_compiler.py
pyportable_installer/compilers/cython_compiler.py
pyportable_installer/compilers/effectless_compiler.py
pyportable_installer/compilers/lib/pyportable_runtime_py310/pyportable_runtime/__init__.py
pyportable_installer/compilers/lib/pyportable_runtime_py310/pyportable_runtime/cipher.pyd
pyportable_installer/compilers/lib/pyportable_runtime_py38/pyportable_runtime/__init__.py
pyportable_installer/compilers/lib/pyportable_runtime_py38/pyportable_runtime/cipher.pyd
pyportable_installer/compilers/lib/pyportable_runtime_py39/pyportable_runtime/__init__.py
pyportable_installer/compilers/lib/pyportable_runtime_py39/pyportable_runtime/cipher.pyd
pyportable_installer/compilers/mypyc_compiler.py
pyportable_installer/compilers/nuitka_compiler.py
pyportable_installer/compilers/pyarmor_compile.py
pyportable_installer/compilers/pyc_compiler.py
pyportable_installer/compilers/pyportable_compiler.py
pyportable_installer/compilers/zipapp.py
pyportable_installer/global_conf.py
pyportable_installer/main.py
pyportable_installer/main_flow/__init__.py
pyportable_installer/main_flow/step1/__init__.py
pyportable_installer/main_flow/step1/indexing_paths.py
pyportable_installer/main_flow/step1/init_key_params.py
pyportable_installer/main_flow/step1/load_conf.py
pyportable_installer/main_flow/step1/main.py
pyportable_installer/main_flow/step1/name_converter.py
pyportable_installer/main_flow/step1/path_formatter.py
pyportable_installer/main_flow/step1/where_is_python.py
pyportable_installer/main_flow/step2/__init__.py
pyportable_installer/main_flow/step2/dist_tree.py
pyportable_installer/main_flow/step2/prebuild_dist_dirs.py
pyportable_installer/main_flow/step3/__init__.py
pyportable_installer/main_flow/step3/build_dist.py
pyportable_installer-4.4.2.dist-info/LICENSE
pyportable_installer-4.4.2.dist-info/WHEEL
pyportable_installer-4.4.2.dist-info/METADATA
pyportable_installer-4.4.2.dist-info/RECORD
