Metadata-Version: 2.1
Name: pyportable-installer
Version: 4.4.2
Summary: Build and distribute portable Python application by all-in-one configuration file.
Home-page: https://github.com/likianta/pyportable-installer
License: MIT
Author: Likianta
Author-email: likianta@foxmail.com
Requires-Python: >=3.8,<4.0
Classifier: License :: OSI Approved :: MIT License
Classifier: Programming Language :: Python :: 3
Classifier: Programming Language :: Python :: 3.8
Classifier: Programming Language :: Python :: 3.9
Classifier: Programming Language :: Python :: 3.10
Classifier: Programming Language :: Python :: 3.11
Provides-Extra: all
Provides-Extra: tml
Provides-Extra: yml
Requires-Dist: argsense (>=0.4.2,<0.5.0)
Requires-Dist: embed-python-manager (>=0.2.8,<0.3.0)
Requires-Dist: gen-exe; platform_system == "Windows"
Requires-Dist: lk-logger (>=5.4.7,<6.0.0)
Requires-Dist: lk-utils (>=2.4.1,<2.5.0)
Requires-Dist: pillow; extra == "all"
Requires-Dist: pyarmor; extra == "all"
Requires-Dist: pyportable-crypto (>=1.0.3,<2.0.0)
Requires-Dist: pysimplegui
Requires-Dist: pyyaml; extra == "all" or extra == "yml"
Requires-Dist: toml; extra == "all" or extra == "tml"
